django_oauth_client-1.0.0-py3.11-nspkg.pth
django_oauth_client/oauth.py
django_oauth_client/settings.py
django_oauth_client/verify_token.py
tests/__init__.py
tests/conftest.py
tests/test_settings.py
tests/test_token_verification.py
django_oauth_client-1.0.0.dist-info/LICENSE
django_oauth_client-1.0.0.dist-info/METADATA
django_oauth_client-1.0.0.dist-info/WHEEL
django_oauth_client-1.0.0.dist-info/namespace_packages.txt
django_oauth_client-1.0.0.dist-info/top_level.txt
django_oauth_client-1.0.0.dist-info/RECORD
