Metadata-Version: 2.1
Name: django-oauth-client
Version: 1.0.0
Summary: Django Authentication
Home-page: http://pypi.python.org/projects/xxxx
Author: Schroeck IT-Consulting GbR
Author-email: hello@schroeck-consulting.de
License: GPL
Classifier: Programming Language :: Python
Classifier: Programming Language :: Python :: 3.9
Classifier: Programming Language :: Python :: 3.10
Classifier: Topic :: Software Development :: Libraries :: Python Modules
License-File: LICENSE
Requires-Dist: Django
Requires-Dist: Authlib
Requires-Dist: requests
Requires-Dist: pyjwt
